ttt_nnouv_nom_gn/__init__.py
ttt_nnouv_nom_gn/sub_package_1/__init__.py
ttt_nnouv_nom_gn/sub_package_1/my_class_1.py
ttt_nnouv_nom_gn/sub_package_2/__init__.py
ttt_nnouv_nom_gn/sub_package_2/my_class_2.py
ttt_nnouv_nom_gn/sub_package_2/my_class_3.py
ttt_nnouv_nom_gn/ttt_nnouv_nom_gn.py
ttt_nnouv_nom_gn-0.1.1.dist-info/LICENSE
ttt_nnouv_nom_gn-0.1.1.dist-info/METADATA
ttt_nnouv_nom_gn-0.1.1.dist-info/WHEEL
ttt_nnouv_nom_gn-0.1.1.dist-info/RECORD
