Metadata-Version: 2.1
Name: ttt-nnouv-nom-gn
Version: 0.1.1
Summary: TTT Test package Guillaume Description
Home-page: https://github.com/guillaumenibert/ttt-nnouv-nom-gn
Author: Guillaume Nibert
Author-email: guillaume.nibert@lip6.fr
Requires-Python: >=3.9,<4.0
Classifier: Programming Language :: Python :: 3
Classifier: Programming Language :: Python :: 3.9
Classifier: Programming Language :: Python :: 3.10
Classifier: Programming Language :: Python :: 3.11
Classifier: Programming Language :: Python :: 3.12
Project-URL: Documentation, https://guillaumenibert.github.io/ttt-nnouv-nom-gn
Project-URL: Repository, https://github.com/guillaumenibert/ttt-nnouv-nom-gn
